spd3303x/__init__.py
spd3303x/cli.py
spd3303x-1.0.3.dist-info/entry_points.txt
spd3303x-1.0.3.dist-info/licenses/LICENSE
spd3303x-1.0.3.dist-info/WHEEL
spd3303x-1.0.3.dist-info/METADATA
spd3303x-1.0.3.dist-info/RECORD
