Metadata-Version: 2.4
Name: spd3303x
Version: 1.0.3
Summary: Python API for SigLent SPD3303X
Author-email: Kai Geissdoerfer <kai.geissdoerfer@tu-dresden.de>
Requires-Python: >=3.10
Classifier: Development Status :: 5 - Production/Stable
Classifier: Intended Audience :: Developers
Classifier: Intended Audience :: Information Technology
Classifier: Programming Language :: Python :: 3
License-File: LICENSE
Requires-Dist: numpy
Requires-Dist: pyvisa-py
Requires-Dist: PyUSB
Requires-Dist: click
Requires-Dist: python-vxi11
Requires-Dist: zeroconf
Requires-Dist: psutil
Requires-Dist: standard-xdrlib; python_version >= '3.13'
Requires-Dist: pytest >= 3.9 ; extra == "test"
Requires-Dist: pytest-runner ; extra == "test"
Provides-Extra: test
